fortscript/__init__.py
fortscript/games.py
fortscript/main.py
fortscript/cli/__init__.py
fortscript/cli/cli.py
fortscript/cli/fortscript.yaml
fortscript/cookbook/project_with_arguments/backend_simulator.py
fortscript/cookbook/project_with_arguments/main.py
fortscript/cookbook/project_with_games_list/backend_simulator.py
fortscript/cookbook/project_with_games_list/main.py
fortscript/cookbook/project_with_yaml_file/config.yaml
fortscript/cookbook/project_with_yaml_file/main.py
fortscript/cookbook/project_with_yaml_file/overlay_controller.py
fortscript-0.4.0.dist-info/METADATA
fortscript-0.4.0.dist-info/WHEEL
fortscript-0.4.0.dist-info/entry_points.txt
fortscript-0.4.0.dist-info/licenses/LICENSE
fortscript-0.4.0.dist-info/RECORD
