Metadata-Version: 2.4
Name: fortscript
Version: 0.4.0
Summary: Pause your scripts automatically when gaming or running heavy apps.
Project-URL: Repository, https://github.com/WesleyQDev/fortscript
Author: Wesley Queiroz
License-Expression: MIT
License-File: LICENSE
Classifier: License :: OSI Approved :: MIT License
Classifier: Operating System :: OS Independent
Classifier: Programming Language :: Python :: 3
Classifier: Programming Language :: Python :: 3.10
Classifier: Programming Language :: Python :: 3.11
Classifier: Programming Language :: Python :: 3.12
Classifier: Programming Language :: Python :: 3.13
Requires-Python: >=3.10
Requires-Dist: psutil>=7.1.3
Requires-Dist: pyyaml>=6.0.3
Requires-Dist: rich>=14.2.0
